core_ftp/__init__.py
core_ftp/py.typed
core_ftp/clients/__init__.py
core_ftp/clients/sftp.py
core_ftp/etls/__init__.py
core_ftp/etls/file_based.py
core_ftp/tests/__init__.py
core_ftp/tests/base.py
core_ftp-2.0.1.dist-info/licenses/LICENSE
core_ftp-2.0.1.dist-info/METADATA
core_ftp-2.0.1.dist-info/WHEEL
core_ftp-2.0.1.dist-info/top_level.txt
core_ftp-2.0.1.dist-info/RECORD
