Metadata-Version: 2.4
Name: core-ftp
Version: 2.0.1
Summary: This project/library contains common elements related to FTP connections...
Author-email: Alejandro Cora González <alek.cora.glez@gmail.com>
Maintainer: Alejandro Cora González
License: MIT
Project-URL: Homepage, https://gitlab.com/bytecode-solutions/core/core-ftp
Project-URL: Repository, https://gitlab.com/bytecode-solutions/core/core-ftp
Project-URL: Documentation, https://core-ftp.readthedocs.io/en/latest/
Project-URL: Issues, https://gitlab.com/bytecode-solutions/core/core-ftp/-/issues
Project-URL: Changelog, https://gitlab.com/bytecode-solutions/core/core-ftp/-/blob/master/CHANGELOG.md
Classifier: License :: OSI Approved :: MIT License
Classifier: Intended Audience :: Developers
Classifier: Development Status :: 5 - Production/Stable
Classifier: Topic :: Software Development :: Libraries :: Python Modules
Classifier: Topic :: Utilities
Classifier: Programming Language :: Python :: 3
Classifier: Programming Language :: Python :: 3 :: Only
Classifier: Programming Language :: Python :: 3.9
Classifier: Programming Language :: Python :: 3.10
Classifier: Programming Language :: Python :: 3.11
Classifier: Programming Language :: Python :: 3.12
Classifier: Programming Language :: Python :: 3.13
Requires-Python: >=3.9
License-File: LICENSE
Requires-Dist: core-etl>=2.0.0
Requires-Dist: core-tests>=2.0.1
Requires-Dist: paramiko>=3.5.0
Requires-Dist: typing-extensions>=4.8.0; python_version >= "3.9" and python_version < "3.11"
Provides-Extra: dev
Requires-Dist: core-dev-tools>=1.0.1; extra == "dev"
Requires-Dist: types-paramiko>=3.5.0.20240918; extra == "dev"
Dynamic: license-file
